odoo/addons/stock_available_to_promise_release_block/README.rst
odoo/addons/stock_available_to_promise_release_block/__init__.py
odoo/addons/stock_available_to_promise_release_block/__manifest__.py
odoo/addons/stock_available_to_promise_release_block/i18n/it.po
odoo/addons/stock_available_to_promise_release_block/i18n/stock_available_to_promise_release_block.pot
odoo/addons/stock_available_to_promise_release_block/models/__init__.py
odoo/addons/stock_available_to_promise_release_block/models/stock_move.py
odoo/addons/stock_available_to_promise_release_block/models/stock_picking.py
odoo/addons/stock_available_to_promise_release_block/models/stock_route.py
odoo/addons/stock_available_to_promise_release_block/models/stock_rule.py
odoo/addons/stock_available_to_promise_release_block/readme/CONTRIBUTORS.rst
odoo/addons/stock_available_to_promise_release_block/readme/DESCRIPTION.rst
odoo/addons/stock_available_to_promise_release_block/readme/USAGE.rst
odoo/addons/stock_available_to_promise_release_block/static/description/icon.png
odoo/addons/stock_available_to_promise_release_block/static/description/index.html
odoo/addons/stock_available_to_promise_release_block/tests/__init__.py
odoo/addons/stock_available_to_promise_release_block/tests/common.py
odoo/addons/stock_available_to_promise_release_block/tests/test_block_release.py
odoo/addons/stock_available_to_promise_release_block/views/stock_move.xml
odoo/addons/stock_available_to_promise_release_block/views/stock_picking.xml
odoo/addons/stock_available_to_promise_release_block/views/stock_route.xml
odoo_addon_stock_available_to_promise_release_block-16.0.1.1.1.2.dist-info/METADATA
odoo_addon_stock_available_to_promise_release_block-16.0.1.1.1.2.dist-info/WHEEL
odoo_addon_stock_available_to_promise_release_block-16.0.1.1.1.2.dist-info/top_level.txt
odoo_addon_stock_available_to_promise_release_block-16.0.1.1.1.2.dist-info/RECORD
